hello.v
module hello(input clk, input rst, output [10:0] cnt); 
reg [10:0] cnt = 0;
always @(posedge clk) begin 
    if (rst) 
        cnt <= 0; 
    else 
        cnt <= cnt + 1; 
end 

`ifdef FORMAL
    assume property (cnt != 10);
    assert property (cnt != 9);
`endif
endmodule

hello/engine_0/trace_induct.vcd
$version Generated by Yosys-SMTBMC $end
$timescale 1ns $end
$var integer 32 t smt_step $end
$var event 1 ! smt_clock $end
$scope module hello $end
$var wire 1 n0 clk $end
$var wire 11 n1 cnt $end
$var wire 1 n2 rst $end
$upscope $end
$enddefinitions $end
#0
1!
b00000000000000000000000000000000 t
b1 n0
b11111111110 n1
b1 n2
#5
b0 n0
#10
1!
b00000000000000000000000000000001 t
b1 n0
b00000000000 n1
b0 n2
#15
b0 n0
#20
1!
b00000000000000000000000000000010 t
b1 n0
b00000000001 n1
b0 n2
#25
b0 n0
#30
1!
b00000000000000000000000000000011 t
b1 n0
b00000000010 n1
b0 n2
#35
b0 n0
#40
1!
b00000000000000000000000000000100 t
b1 n0
b00000000011 n1
b0 n2
#45
b0 n0
#50
1!
b00000000000000000000000000000101 t
b1 n0
b00000000100 n1
b0 n2
#55
b0 n0
#60
1!
b00000000000000000000000000000110 t
b1 n0
b00000000101 n1
b0 n2
#65
b0 n0
#70
1!
b00000000000000000000000000000111 t
b1 n0
b00000000110 n1
b0 n2
#75
b0 n0
#80
1!
b00000000000000000000000000001000 t
b1 n0
b00000000111 n1
b0 n2
#85
b0 n0
#90
1!
b00000000000000000000000000001001 t
b1 n0
b00000001000 n1
b0 n2
#95
b0 n0
#100
1!
b00000000000000000000000000001010 t
b1 n0
b00000001001 n1
b0 n2
#105
b0 n0
#110
1!
b00000000000000000000000000001011 t
b1 n0
